Wizard/ConfigHandler.py
Wizard/__init__.py
configwizard/ConfigHandler.py
configwizard/__init__.py
configwizard-1.0.5.dist-info/LICENSE
configwizard-1.0.5.dist-info/METADATA
configwizard-1.0.5.dist-info/WHEEL
configwizard-1.0.5.dist-info/top_level.txt
configwizard-1.0.5.dist-info/RECORD
