Metadata-Version: 2.1
Name: configwizard
Version: 1.0.5
Summary: A package for handling configuration files
Home-page: https://github.com/LapisPhoenix/ConfigWizard
Author: Lapis Pheonix
Classifier: Development Status :: 3 - Alpha
Classifier: Intended Audience :: Developers
Classifier: License :: OSI Approved :: MIT License
Classifier: Programming Language :: Python :: 3
Classifier: Programming Language :: Python :: 3.11
Requires-Python: >=3.11.3
License-File: LICENSE
Requires-Dist: tomli-w
